pocs_based_clustering/__init__.py
pocs_based_clustering/tools.py
pocs_based_clustering-1.3.1.dist-info/LICENSE
pocs_based_clustering-1.3.1.dist-info/METADATA
pocs_based_clustering-1.3.1.dist-info/WHEEL
pocs_based_clustering-1.3.1.dist-info/top_level.txt
pocs_based_clustering-1.3.1.dist-info/RECORD
