Metadata-Version: 2.1
Name: pocs-based-clustering
Version: 1.3.1
Summary: Official Implementation of POCS-based Clustering Algorithm
Home-page: https://github.com/tranleanh/pocs-based-clustering
Author: Le-Anh Tran
Author-email: leanhtran@mju.ac.kr
Classifier: Programming Language :: Python :: 3
Classifier: License :: OSI Approved :: Apache Software License
Classifier: Operating System :: Microsoft :: Windows :: Windows 10
License-File: LICENSE
